{
	"bigzBSayhQyHPQScBwgYRb": {
		"firstPlayed": "2023-12-02T07:20:22.687Z",
		"lastPlayed": "2023-12-02T18:19:52.647Z",
		"totalPlayed": 52
	},
	"4pkSUP7cXQgNbviGULCszn": {
		"firstPlayed": "2023-12-02T14:26:40.548Z",
		"lastPlayed": "2023-12-02T18:18:31.248Z",
		"totalPlayed": 1
	},
	"kYLBo4rkLefLXzQ1kqdisR": {
		"firstPlayed": "2023-12-02T17:33:43.907Z",
		"lastPlayed": "2023-12-02T17:36:48.160Z",
		"totalPlayed": 0
	},
	"cEqrsLrBcSfGh7XpzZEq4X": {
		"firstPlayed": "2023-12-02T17:48:08.904Z",
		"lastPlayed": "2023-12-02T18:18:56.450Z",
		"totalPlayed": 6
	}
}